scan/__init__.py
scan/amazon.py
scan/barcode.py
scan/dms.py
scan/dms_views.py
scan/entity_view.py
scan/folderwatcher.py
scan/logger.py
scan/pdf.py
scan/product.py
scan/profiler.py
scan/scan_cmd.py
scan/scan_webserver.py
scan/scans.py
scan/upload.py
scan/upload_job.py
scan/version.py
scan/webcam.py
scan2wiki_examples/2015_11_14_17_53_37.pdf
scan2wiki_examples/2015_11_14_17_53_37.txt
scan2wiki_examples/2016_01_17_09_32_49.jpg
scan2wiki_examples/2021/2021_10_20_15_51_33.pdf
scan2wiki_examples/2021/2021_10_20_15_51_33.txt
scan2wiki_examples/2021/2021_11_01_13_03_50.pdf
scan2wiki_examples/2021/2021_11_01_13_03_50.txt
scan2wiki_examples/barcodes/passengers_barcode.jpg
scan2wiki_examples/barcodes/webcam_2023-11-16_105755.jpg
scan2wiki-0.4.0.dist-info/METADATA
scan2wiki-0.4.0.dist-info/WHEEL
scan2wiki-0.4.0.dist-info/entry_points.txt
scan2wiki-0.4.0.dist-info/licenses/LICENSE
scan2wiki-0.4.0.dist-info/RECORD
