Metadata-Version: 2.4
Name: scan2wiki
Version: 0.4.0
Summary: scan2wiki - nicegui based DMS with option to scan documents to a semantic mediawiki
Project-URL: Home, https://github.com/WolfgangFahl/scan2wiki
Project-URL: Documentation, https://wiki.bitplan.com/index.php/scan2wiki
Project-URL: Source, https://github.com/WolfgangFahl/scan2wiki
Author-email: Wolfgang Fahl <wf@WolfgangFahl.com>
Maintainer-email: Wolfgang Fahl <wf@WolfgangFahl.com>
License: Apache-2.0
License-File: LICENSE
Keywords: DMS,OCR,mediawiki,nicegui,scan
Classifier: Development Status :: 4 - Beta
Classifier: Environment :: Web Environment
Classifier: Intended Audience :: Developers
Classifier: Intended Audience :: Education
Classifier: Intended Audience :: Science/Research
Classifier: License :: OSI Approved :: Apache Software License
Classifier: Operating System :: OS Independent
Classifier: Programming Language :: Python :: 3 :: Only
Classifier: Programming Language :: Python :: 3.10
Classifier: Programming Language :: Python :: 3.11
Classifier: Programming Language :: Python :: 3.12
Classifier: Programming Language :: Python :: 3.13
Classifier: Topic :: Software Development :: User Interfaces
Requires-Python: >=3.10
Requires-Dist: apscheduler
Requires-Dist: beautifulsoup4>=4.11.1
Requires-Dist: dataclasses-json>=0.6.1
Requires-Dist: ngwidgets>=0.27.1
Requires-Dist: py-3rdparty-mediawiki>=0.15.4
Requires-Dist: pybasemkit>=0.0.3
Requires-Dist: pylodstorage>=0.16.4
Requires-Dist: pymupdf>=1.25.5
Requires-Dist: pyzbar>=0.1.9
Requires-Dist: watchdog
Provides-Extra: test
Requires-Dist: green; extra == 'test'
